drb/drivers/grib/__init__.py
drb/drivers/grib/_version.py
drb/drivers/grib/grib_common.py
drb/drivers/grib/grib_node.py
drb/drivers/grib/grib_node_factory.py
drb/exceptions/grib.py
drb/topics/grib/__init__.py
drb/topics/grib/cortex.yml
drb_driver_grib-1.3.0.dist-info/LICENCE.txt
drb_driver_grib-1.3.0.dist-info/METADATA
drb_driver_grib-1.3.0.dist-info/WHEEL
drb_driver_grib-1.3.0.dist-info/entry_points.txt
drb_driver_grib-1.3.0.dist-info/top_level.txt
drb_driver_grib-1.3.0.dist-info/RECORD
