Metadata-Version: 2.1
Name: drb-driver-grib
Version: 1.3.0
Summary: DRB GRIB driver
Author: GAEL Systems
Author-email: drb-python@gael.fr
License: LGPLv3
Project-URL: Documentation, http://drb-python.gitlab.io/impl/grib
Project-URL: Source, https://gitlab.com/drb-python/impl/grib
Classifier: Programming Language :: Python :: 3.8
Classifier: Environment :: Plugins
Classifier: License :: OSI Approved :: GNU Lesser General Public License v3 (LGPLv3)
Requires-Python: >=3.8
License-File: LICENCE.txt
Requires-Dist: drb ~=2.2.0
Requires-Dist: numpy >=1.21.2
Requires-Dist: xarray >=0.19.0
Requires-Dist: cfgrib >=0.9.10.1
Requires-Dist: ecmwflibs >=0.4.17
Requires-Dist: eccodes >=1.5.1
